google/__init__.py
google/refine/__init__.py
google/refine/__main__.py
google/refine/cli.py
google/refine/facet.py
google/refine/history.py
google/refine/refine.py
openrefine_client-0.3.10.dist-info/COPYING.txt
openrefine_client-0.3.10.dist-info/METADATA
openrefine_client-0.3.10.dist-info/WHEEL
openrefine_client-0.3.10.dist-info/entry_points.txt
openrefine_client-0.3.10.dist-info/top_level.txt
openrefine_client-0.3.10.dist-info/RECORD
