Metadata-Version: 2.1
Name: openrefine-client
Version: 0.3.10
Summary: The OpenRefine Python Client Library provides an interface to communicating with an OpenRefine server. This fork extends the command line interface (CLI).
Home-page: https://github.com/opencultureconsulting/openrefine-client
Author: Felix Lohmeier
Author-email: felix.lohmeier@opencultureconsulting.com
License: UNKNOWN
Keywords: openrefine client batch processing docker etl code4lib
Platform: Any
Classifier: Development Status :: 4 - Beta
Classifier: Intended Audience :: Developers
Classifier: Intended Audience :: System Administrators
Classifier: License :: OSI Approved :: GNU General Public License (GPL)
Classifier: License :: OSI Approved :: GNU General Public License v3 or later (GPLv3+)
Classifier: Operating System :: OS Independent
Classifier: Programming Language :: Python
Classifier: Programming Language :: Python :: 2
Classifier: Programming Language :: Python :: 2.7
Classifier: Topic :: Software Development :: Libraries :: Python Modules
Classifier: Topic :: Text Processing
Requires-Python: >=2.7, !=3.*
Requires-Dist: urllib2-file
